[
null,
{"id":1,"expanded":true,"name":"TestMap1","order":1,"parentId":0,"scrollX":818.5,"scrollY":461},
{"id":2,"expanded":true,"name":"CarCrash","order":4,"parentId":0,"scrollX":818.5,"scrollY":461},
{"id":3,"expanded":true,"name":"Outside Gas","order":5,"parentId":0,"scrollX":810.5,"scrollY":499},
{"id":4,"expanded":true,"name":"Gas Station Indoors","order":6,"parentId":0,"scrollX":691,"scrollY":946},
{"id":5,"expanded":false,"name":"Tileset Testing","order":3,"parentId":1,"scrollX":699,"scrollY":446},
{"id":6,"expanded":false,"name":"Test Map A","order":2,"parentId":1,"scrollX":818.5,"scrollY":461},
{"id":7,"expanded":true,"name":"Overworld Part 1","order":7,"parentId":0,"scrollX":2003.5,"scrollY":1360},
{"id":8,"expanded":false,"name":"Rose Maze","order":8,"parentId":0,"scrollX":1493.5,"scrollY":823},
{"id":9,"expanded":false,"name":"Movie/Start","order":9,"parentId":0,"scrollX":832,"scrollY":640},
{"id":10,"expanded":false,"name":"Overworld Part 2","order":10,"parentId":0,"scrollX":1390.2,"scrollY":543.6},
{"id":11,"expanded":false,"name":"Farmhouse","order":11,"parentId":0,"scrollX":982.1999999999999,"scrollY":553.1999999999999}
]